listmonk_api/__init__.py
listmonk_api/decorators.py
listmonk_api/exceptions.py
listmonk_api/listmonk_api.py
listmonk_api/version.py
listmonk_api-0.3.1.dist-info/LICENSE
listmonk_api-0.3.1.dist-info/METADATA
listmonk_api-0.3.1.dist-info/WHEEL
listmonk_api-0.3.1.dist-info/top_level.txt
listmonk_api-0.3.1.dist-info/RECORD
